iisignature_tensorflow_2/__init__.py
iisignature_tensorflow_2-0.1.0.dist-info/METADATA
iisignature_tensorflow_2-0.1.0.dist-info/WHEEL
iisignature_tensorflow_2-0.1.0.dist-info/RECORD
