Metadata-Version: 2.1
Name: iisignature_tensorflow_2
Version: 0.1.0
Summary: Tensorflow 2 implementation of the iisignature package.
Author: Rémi Genet
Requires-Python: >=3.10,<4.0
Classifier: Programming Language :: Python :: 3
Classifier: Programming Language :: Python :: 3.10
Classifier: Programming Language :: Python :: 3.11
Classifier: Programming Language :: Python :: 3.12
Requires-Dist: iisignature (>=0.24)
Requires-Dist: numpy (>=1.2,<2)
Requires-Dist: tensorflow (>=2.8,<3)
